todot/__init__.py
todot/__main__.py
todot/cli.py
todot/constants.py
todot/finder.py
todot/parser.py
todot/printer.py
todot/todo.py
todot_python-0.1.0.dist-info/LICENSE
todot_python-0.1.0.dist-info/METADATA
todot_python-0.1.0.dist-info/WHEEL
todot_python-0.1.0.dist-info/entry_points.txt
todot_python-0.1.0.dist-info/top_level.txt
todot_python-0.1.0.dist-info/RECORD
