Metadata-Version: 2.1
Name: todot-python
Version: 0.1.0
Summary: A powerful tool to parse TODOs/FIXMEs etc. from source files
Home-page: https://wasi-master.github.io/todot/
Author: Wasi Master
Author-email: arianmollik323@gmail.com
License: MIT
Project-URL: Bug Tracker, https://github.com/wasi-master/todot/issues
Project-URL: Source, https://github.com/wasi-master/todot
Project-URL: Documentation, https://wasi-master.github.io/todot/
Project-URL: Say Thanks, https://saythanks.io/to/arianmollik323@gmail.com
Platform: UNKNOWN
Classifier: Programming Language :: Python :: 3.6
Classifier: License :: OSI Approved :: MIT License
Classifier: Operating System :: OS Independent
Classifier: Development Status :: 4 - Beta
Classifier: Environment :: Console
Classifier: Intended Audience :: Developers
Classifier: Intended Audience :: End Users/Desktop
Classifier: Natural Language :: English
Classifier: Topic :: Terminals
Requires-Python: >=3.6
License-File: LICENSE
